littrs/__init__.py
littrs/littrs.cpython-312-x86_64-linux-gnu.so
littrs-0.3.0.dist-info/METADATA
littrs-0.3.0.dist-info/WHEEL
littrs-0.3.0.dist-info/RECORD
