Metadata-Version: 2.4
Name: littrs
Version: 0.3.0
Classifier: Development Status :: 4 - Beta
Classifier: Intended Audience :: Developers
Classifier: License :: OSI Approved :: Apache Software License
Classifier: Programming Language :: Python :: 3
Classifier: Programming Language :: Python :: 3.9
Classifier: Programming Language :: Python :: 3.10
Classifier: Programming Language :: Python :: 3.11
Classifier: Programming Language :: Python :: 3.12
Classifier: Programming Language :: Python :: 3.13
Classifier: Programming Language :: Rust
Classifier: Topic :: Security
Classifier: Topic :: Software Development :: Interpreters
Summary: A minimal, secure Python sandbox for AI agents
Keywords: sandbox,security,python,interpreter,ai,agents
License: Apache-2.0
Requires-Python: >=3.9
Project-URL: Homepage, https://github.com/chonkie-inc/littrs
Project-URL: Issues, https://github.com/chonkie-inc/littrs/issues
Project-URL: Repository, https://github.com/chonkie-inc/littrs
